{
    "Title": "The General's Daughter",
    "Overview": "When the body of Army Capt. Elizabeth Campbell is found on a Georgia military base, two investigators, Warrant Officers Paul Brenner and Sara Sunhill, are ordered to solve her murder. What they uncover is anything but clear-cut. Unseemly details emerge about Campbell's life, leading to allegations of a possible military coverup of her death and the involvement of her father, Lt. Gen. Joseph Campbell.",
    "Tagline": "Go behind the lies.",
    "Homepage": "Unknown",
    "Release_Date": "1999-06-18",
    "Vote_Average": 6.382,
    "Runtime": 116,
    "Poster_Path": "/yGQ26eQUPaU2cWpZsdn2RgSOj0D.jpg",
    "Genres": "Thriller, Mystery, Drama, Crime",
    "Keywords": "[{\"id\": 236, \"name\": \"suicide\"}, {\"id\": 703, \"name\": \"detective\"}, {\"id\": 818, \"name\": \"based on novel\"}, {\"id\": 910, \"name\": \"bondage\"}, {\"id\": 1402, \"name\": \"general\"}, {\"id\": 2340, \"name\": \"paranoia\"}, {\"id\": 2483, \"name\": \"nudity\"}, {\"id\": 4595, \"name\": \"u.s. army\"}, {\"id\": 5340, \"name\": \"investigation\"}, {\"id\": 6078, \"name\": \"politics\"}, {\"id\": 9665, \"name\": \"cover-up\"}, {\"id\": 9826, \"name\": \"murder\"}, {\"id\": 10085, \"name\": \"betrayal\"}, {\"id\": 10410, \"name\": \"conspiracy\"}, {\"id\": 12365, \"name\": \"gang rape\"}, {\"id\": 15300, \"name\": \"father daughter relationship\"}, {\"id\": 177185, \"name\": \"videotape\"}, {\"id\": 227890, \"name\": \"military law\"}]",
    "Director": "Simon West",
    "budget": 60000000,
    "revenue": 149705852,
    "production_companies": "Paramount Pictures, MFP Munich Film Partners GmbH & Company I. Produktions KG, Krane Entertainment, Neufeld Rehme Productions",
    "Cast": "John Travolta, Madeleine Stowe, James Cromwell"
}