{
    "Title": "Men of Honor",
    "Overview": "Against formidable odds -- and an old-school diving instructor embittered by the U.S. Navy's new, less prejudicial policies -- Carl Brashear sets his sights on becoming the Navy's first African-American master diver in this uplifting true story. Their relationship starts out on the rocks, but fate ultimately conspires to bring the men together into a setting of mutual respect, triumph and honor.",
    "Tagline": "History is made by those who break the rules.",
    "Homepage": "Unknown",
    "Release_Date": "2000-09-13",
    "Vote_Average": 7.46,
    "Runtime": 129,
    "Poster_Path": "/wNUAnXV1mzOOfvnVBIYsalkk078.jpg",
    "Genres": "Drama",
    "Keywords": "[{\"id\": 269, \"name\": \"diving\"}, {\"id\": 4410, \"name\": \"u.s. navy\"}]",
    "Director": "George Tillman, Jr.",
    "budget": 32000000,
    "revenue": 48814909,
    "production_companies": "Fox 2000 Pictures",
    "Cast": "Robert De Niro, Cuba Gooding Jr., Charlize Theron",
    "clean_text": "man honor formidable odd   oldschool diving instructor embitter navys new prejudicial policy   carl brashear set sight navys first africanamerican master diver uplift true story relationship start rock fate ultimately conspire bring man setting mutual respect triumph honor history break rule drama george tillman jr robert de niro cuba gooding jr charlize theron 2000"
}