{
    "Title": "Blue Jasmine",
    "Overview": "After experiencing a traumatic misfortune, Jasmine French, a wealthy woman from New York, moves to San Francisco to live with her foster sister Ginger and the firm purpose of getting a new life, but she will be haunted by anxiety and memories of the past.",
    "Tagline": "Unknown",
    "Homepage": "http://www.sonyclassics.com/bluejasmine",
    "Release_Date": "2013-08-01",
    "Vote_Average": 6.998,
    "Runtime": 99,
    "Poster_Path": "/zLdLiUJfueZBctdv8OvkmGXEHEC.jpg",
    "Genres": "Drama",
    "Keywords": "san francisco, sister sister relationship, new york city, rich, narcissism, xanax",
    "Director": "Woody Allen",
    "budget": 18000000,
    "revenue": 99206215,
    "production_companies": "Perdido Productions",
    "Cast": "Cate Blanchett, Alec Baldwin, Sally Hawkins"
}