{
    "Title": "The Beyond",
    "Overview": "A young woman inherits an old hotel in Louisiana where, following a series of supernatural \"accidents\", she learns that the building was built over one of the entrances to Hell.",
    "Tagline": "Beyond death... Beyond Evil... Beyond the dreaded gates of hell.",
    "Homepage": "Unknown",
    "Release_Date": "1981-04-29",
    "Vote_Average": 6.9,
    "Runtime": 88,
    "Poster_Path": "/uCsD8NCHR17sQNzcY60MINa7L3s.jpg",
    "Genres": "Horror",
    "Keywords": "[{\"id\": 612, \"name\": \"hotel\"}, {\"id\": 1706, \"name\": \"experiment\"}, {\"id\": 6154, \"name\": \"hell\"}, {\"id\": 10292, \"name\": \"gore\"}, {\"id\": 10326, \"name\": \"morgue\"}, {\"id\": 10327, \"name\": \"undead\"}, {\"id\": 11221, \"name\": \"blood\"}, {\"id\": 12377, \"name\": \"zombie\"}, {\"id\": 14819, \"name\": \"violence\"}, {\"id\": 15032, \"name\": \"gothic horror\"}, {\"id\": 33505, \"name\": \"gothic\"}, {\"id\": 157512, \"name\": \"mutilation\"}, {\"id\": 162846, \"name\": \"ghost\"}, {\"id\": 164092, \"name\": \"blindness\"}, {\"id\": 189921, \"name\": \"video nasty\"}, {\"id\": 208580, \"name\": \"acid\"}, {\"id\": 210162, \"name\": \"grim\"}, {\"id\": 210163, \"name\": \"dire\"}, {\"id\": 215305, \"name\": \"entrails\"}]",
    "Director": "Lucio Fulci",
    "budget": 0,
    "revenue": 0,
    "production_companies": "Fulvia Film",
    "Cast": "Catriona MacColl, David Warbeck, Cinzia Monreale",
    "clean_text": "young woman inherit old hotel louisiana follow series supernatural accident learn building build one entrance hell death evil dread gate hell horror lucio fulci catriona maccoll david warbeck cinzia monreale 1981"
}