{
    "Title": "Mean Girls",
    "Overview": "Cady Heron is a hit with The Plastics, the A-list girl clique at her new school, until she makes the mistake of falling for Aaron Samuels, the ex-boyfriend of alpha Plastic Regina George.",
    "Tagline": "Welcome to girl world.",
    "Homepage": "http://www.meangirls.com/",
    "Release_Date": "2004-04-30",
    "Vote_Average": 7.186,
    "Runtime": 97,
    "Poster_Path": "/2ZkuQXvVhh45uSvkBej4S7Ix1NJ.jpg",
    "Genres": "Comedy",
    "Keywords": "[{\"id\": 5248, \"name\": \"female friendship\"}, {\"id\": 6270, \"name\": \"high school\"}, {\"id\": 11860, \"name\": \"fish out of water\"}, {\"id\": 12392, \"name\": \"best friend\"}, {\"id\": 13130, \"name\": \"teenager\"}, {\"id\": 15402, \"name\": \"popularity\"}, {\"id\": 18453, \"name\": \"gossip\"}, {\"id\": 155722, \"name\": \"teen comedy\"}, {\"id\": 189964, \"name\": \"high school rivalry\"}, {\"id\": 190141, \"name\": \"new girl at school\"}]",
    "Director": "Mark Waters",
    "budget": 17000000,
    "revenue": 129042871,
    "production_companies": "Paramount Pictures, Broadway Video, M.G. Films",
    "Cast": "Lindsay Lohan, Rachel McAdams, Tim Meadows",
    "clean_text": "mean girl cady heron hit plastic alist girl clique new school make mistake fall aaron samuel exboyfriend alpha plastic regina george welcome girl world comedy mark water lindsay lohan rachel mcadams tim meadow 2004"
}