{
    "Title": "Fantasia 2000",
    "Overview": "Blending lively music and brilliant animation, this sequel to the original 'Fantasia' restores 'The Sorcerer's Apprentice' and adds seven new shorts.",
    "Tagline": "Unknown",
    "Homepage": "http://movies.disney.com/fantasia-2000",
    "Release_Date": "1999-12-31",
    "Vote_Average": 6.994,
    "Runtime": 74,
    "Poster_Path": "/6JszBEg8OEbkMzpY5IPTMVzxmYZ.jpg",
    "Genres": "Animation, Family, Music",
    "Keywords": "[{\"id\": 3537, \"name\": \"orchestra\"}, {\"id\": 190719, \"name\": \"musical segments\"}]",
    "Director": "James Algar",
    "budget": 80000000,
    "revenue": 90874570,
    "production_companies": "Walt Disney Pictures",
    "Cast": "Steve Martin, Itzhak Perlman, Quincy Jones"
}