{
    "Title": "Stand by Me",
    "Overview": "Gordie, Chris, Teddy and Vern are four friends who decide to hike to find the corpse of Ray Brower, a local teenager, who was hit by a train while plucking blueberries in the wild.",
    "Tagline": "For some, it's the last real taste of innocence, and the first real taste of life.",
    "Homepage": "Unknown",
    "Release_Date": "1986-08-08",
    "Vote_Average": 7.856,
    "Runtime": 89,
    "Poster_Path": "/vz0w9BSehcqjDcJOjRaCk7fgJe7.jpg",
    "Genres": "Crime, Drama",
    "Keywords": "[{\"id\": 818, \"name\": \"based on novel\"}, {\"id\": 6054, \"name\": \"friendship\"}, {\"id\": 10683, \"name\": \"coming of age\"}, {\"id\": 169875, \"name\": \"railroad track\"}, {\"id\": 169878, \"name\": \"story within the story\"}, {\"id\": 169885, \"name\": \"\\u00a0flipping coin\"}, {\"id\": 169886, \"name\": \"campfire story\"}, {\"id\": 169887, \"name\": \"reference to superman\"}, {\"id\": 169895, \"name\": \"normandy beach\"}, {\"id\": 208349, \"name\": \"child\"}, {\"id\": 208611, \"name\": \"1950s\"}, {\"id\": 216919, \"name\": \"boys\"}]",
    "Director": "Rob Reiner",
    "budget": 8000000,
    "revenue": 52287414,
    "production_companies": "Columbia Pictures, Act III Communications, The Body, Act III",
    "Cast": "Wil Wheaton, River Phoenix, Corey Feldman",
    "clean_text": "stand gordie chris teddy vern four friend decide hike find corpse ray brower local teenager hit train pluck blueberry wild real taste innocence first real taste life crime drama rob reiner wil wheaton river phoenix corey feldman 1986"
}