{
    "Title": "Seven Psychopaths",
    "Overview": "A struggling screenwriter inadvertently becomes entangled in the Los Angeles criminal underworld after his oddball friends kidnap a gangster's beloved Shih Tzu.",
    "Tagline": "They Won't Take Any Shih Tzu.",
    "Homepage": "http://www.sevenpsychopaths.com/",
    "Release_Date": "2012-10-12",
    "Vote_Average": 6.809,
    "Runtime": 110,
    "Poster_Path": "/cfkdwxJd1gWGmT9kI0XXYfXNLmw.jpg",
    "Genres": "Comedy, Crime",
    "Keywords": "[{\"id\": 236, \"name\": \"suicide\"}, {\"id\": 567, \"name\": \"alcohol\"}, {\"id\": 572, \"name\": \"sex\"}, {\"id\": 888, \"name\": \"screenwriter\"}, {\"id\": 1449, \"name\": \"underworld\"}, {\"id\": 1721, \"name\": \"fight\"}, {\"id\": 1930, \"name\": \"kidnapping\"}, {\"id\": 8508, \"name\": \"party\"}, {\"id\": 9826, \"name\": \"murder\"}, {\"id\": 11454, \"name\": \"scam\"}, {\"id\": 12670, \"name\": \"los angeles\"}, {\"id\": 13142, \"name\": \"gangster\"}, {\"id\": 14601, \"name\": \"explosion\"}, {\"id\": 15009, \"name\": \"criminal\"}, {\"id\": 186892, \"name\": \"shih tzu\"}, {\"id\": 201858, \"name\": \"struggling\"}]",
    "Director": "Martin McDonagh",
    "budget": 15000000,
    "revenue": 19422261,
    "production_companies": "Blueprint Pictures, CBS Films, British Film Institute (BFI), Film4",
    "Cast": "Colin Farrell, Sam Rockwell, Woody Harrelson",
    "clean_text": "seven psychopath struggle screenwriter inadvertently entangle los angeles criminal underworld oddball friend kidnap gangster belove shih tzu will not shih tzu comedy crime martin mcdonagh colin farrell sam rockwell woody harrelson 2012"
}