{
    "Title": "1941",
    "Overview": "In the days after the attack on Pearl Harbor, panic grips California, where a military officer leads a mob chasing a Japanese sub.",
    "Tagline": "Paranoia meets pandemonium.",
    "Homepage": "Unknown",
    "Release_Date": "1979-12-14",
    "Vote_Average": 5.851,
    "Runtime": 118,
    "Poster_Path": "/52Bn5yC6IHQuVxPUza3Q6RZCZTu.jpg",
    "Genres": "Comedy, War",
    "Keywords": "[{\"id\": 339, \"name\": \"submarine\"}, {\"id\": 387, \"name\": \"california\"}, {\"id\": 1956, \"name\": \"world war ii\"}, {\"id\": 2770, \"name\": \"war ship\"}, {\"id\": 3365, \"name\": \"pearl harbor\"}, {\"id\": 8201, \"name\": \"satire\"}, {\"id\": 12670, \"name\": \"los angeles\"}, {\"id\": 236316, \"name\": \"anarchic comedy\"}]",
    "Director": "Steven Spielberg",
    "budget": 35000000,
    "revenue": 31755742,
    "production_companies": "Columbia Pictures, Universal Pictures, A-Team",
    "Cast": "Dan Aykroyd, Ned Beatty, John Belushi",
    "clean_text": "1941 day attack pearl harbor panic grips california military officer lead mob chase japanese sub paranoia meet pandemonium comedy war steven spielberg dan aykroyd ne beatty john belushi 1979"
}