{
    "Title": "Spy Kids: All the Time in the World",
    "Overview": "Eight years after the third film, the OSS has become the world's top spy agency, while the Spy Kids department has since become defunct. A retired spy Marissa is thrown back into the action along with her stepchildren when a maniacal Timekeeper attempts to take over the world. In order to save the world, Rebecca and Cecil must team up with their hated stepmother. Carmen and Juni have since also grown up and will provide gadgets to them.",
    "Tagline": "Unknown",
    "Homepage": "http://spykidsmovie.net/",
    "Release_Date": "2011-08-18",
    "Vote_Average": 4.691,
    "Runtime": 89,
    "Poster_Path": "/9pUVarhiXfCu8amjmyadzJJJITi.jpg",
    "Genres": "Family, Comedy, Action",
    "Keywords": "[{\"id\": 470, \"name\": \"spy\"}, {\"id\": 3650, \"name\": \"child hero\"}, {\"id\": 4289, \"name\": \"secret agent\"}, {\"id\": 11134, \"name\": \"espionage\"}]",
    "Director": "Robert Rodriguez",
    "budget": 27000000,
    "revenue": 85564310,
    "production_companies": "Dimension Films",
    "Cast": "Jessica Alba, Mason Cook, Rowan Blanchard",
    "clean_text": "spy kid time world eight year third film oss world spy agency spy kids department defunct retired spy marissa throw action stepchildren maniacal timekeeper attempt world order save world rebecca cecil team hat stepmother carman juni grow provide gadget unknown family comedy action robert rodriguez jessica alba mason cook rowan blanchard 2011"
}