{
    "Title": "There's Something About Mary",
    "Overview": "For Ted, prom night went about as bad as it\u2019s possible for any night to go. Thirteen years later, he finally gets another chance with his old prom date, only to run up against other suitors including the sleazy detective he hired to find her.",
    "Tagline": "Love Is In The Hair.",
    "Homepage": "http://www.aboutmary.com/",
    "Release_Date": "1998-07-15",
    "Vote_Average": 6.585,
    "Runtime": 119,
    "Poster_Path": "/g03pwohXHOI75InM3zraiaEGguO.jpg",
    "Genres": "Romance, Comedy",
    "Keywords": "surgeon, stalker, romantic comedy, dream girl, taboo, screwball comedy, frisbee, troubadour, gross out comedy, intellectual disability",
    "Director": "Bobby Farrelly",
    "budget": 23000000,
    "revenue": 369884651,
    "production_companies": "Twentieth Century Fox Film Corporation",
    "Cast": "Cameron Diaz, Ben Stiller, Matt Dillon"
}