{
    "Title": "Meet the Spartans",
    "Overview": "The heroic Leonidas, armed with nothing but leather underwear and a cape, leads a ragtag group of 13 Spartans to defend their homeland against the invading Persians (whose ranks include Ghost Rider, Rocky Balboa, the Transformers, and a hunchbacked Paris Hilton). No one is safe when the Spartans take on the biggest icons in pop culture!",
    "Tagline": "The bigger the hit, the harder they fall.",
    "Homepage": "https://www.newregency.com/movies/meet-the-spartans",
    "Release_Date": "2008-01-24",
    "Vote_Average": 4.031,
    "Runtime": 84,
    "Poster_Path": "/DWQOjAPvM8Kk1Qp3Xq0zae0Z6w.jpg",
    "Genres": "Comedy",
    "Keywords": "[{\"id\": 1721, \"name\": \"fight\"}, {\"id\": 2011, \"name\": \"queen\"}, {\"id\": 3028, \"name\": \"penguin\"}, {\"id\": 4380, \"name\": \"black hole\"}, {\"id\": 5458, \"name\": \"men\"}, {\"id\": 6092, \"name\": \"army\"}, {\"id\": 171603, \"name\": \"s.a.t.\"}, {\"id\": 179430, \"name\": \"aftercreditsstinger\"}, {\"id\": 179431, \"name\": \"duringcreditsstinger\"}]",
    "Director": "Jason Friedberg",
    "budget": 30000000,
    "revenue": 84646831,
    "production_companies": "Regency Enterprises, New Regency Pictures",
    "Cast": "Sean Maguire, Carmen Electra, Ken Davitian",
    "clean_text": "meet spartan heroic leonida arm leather underwear cape lead ragtag group 13 spartan defend homeland invade persian rank include ghost rider rocky balboa transformer hunchbacked paris hilton one safe spartan big icon pop culture big hit hard fall comedy jason friedberg sean maguire carman electra ken davitian 2008"
}