{
    "Title": "Gosford Park",
    "Overview": "In 1930\u2019s England, a group of pretentious rich and famous gather together for a weekend of relaxation at a hunting resort. But when a murder occurs, each one of these interesting characters becomes a suspect.",
    "Tagline": "Tea at four. Dinner at eight. Murder at midnight.",
    "Homepage": "Unknown",
    "Release_Date": "2001-11-07",
    "Vote_Average": 6.856,
    "Runtime": 137,
    "Poster_Path": "/7r8DeZuaaHCiOEbkqZC6MFmwJ69.jpg",
    "Genres": "Drama, Mystery, Thriller",
    "Keywords": "[{\"id\": 964, \"name\": \"servant\"}, {\"id\": 10594, \"name\": \"money\"}, {\"id\": 154976, \"name\": \"shooting party\"}]",
    "Director": "Robert Altman",
    "budget": 19800000,
    "revenue": 87754044,
    "production_companies": "USA Films",
    "Cast": "Helen Mirren, Clive Owen, Maggie Smith"
}