{
    "Title": "Modern Times",
    "Overview": "The Tramp struggles to live in modern industrial society with the help of a young homeless woman.",
    "Tagline": "He stands alone as the greatest entertainer of modern times! No one on earth can make you laugh as heartily or touch your heart as deeply...the whole world laughs, cries and thrills to his priceless genius!",
    "Homepage": "Unknown",
    "Release_Date": "1936-02-05",
    "Vote_Average": 8.293,
    "Runtime": 87,
    "Poster_Path": "/7uoiKOEjxBBW0AgDGQWrlfGQ90w.jpg",
    "Genres": "Comedy, Drama",
    "Keywords": "factory, ambulance, invention, tramp, great depression, industrial revolution, slapstick, machine, pardon, guilty",
    "Director": "Charlie Chaplin",
    "budget": 1,
    "revenue": 8500000,
    "production_companies": "United Artists, Charles Chaplin Productions",
    "Cast": "Charlie Chaplin, Paulette Goddard, Henry Bergman"
}