{
    "Title": "Bring It On",
    "Overview": "The Toro cheerleading squad from Rancho Carne High School in San Diego has got spirit, spunk, sass and a killer routine that's sure to land them the national championship trophy for the sixth year in a row. But for newly-elected team captain Torrance, the Toros' road to total cheer glory takes a shady turn when she discovers that their perfectly-choreographed routines were in fact stolen.",
    "Tagline": "May the best moves win.",
    "Homepage": "https://www.uphe.com/movies/bring-it-on",
    "Release_Date": "2000-08-25",
    "Vote_Average": 6.225,
    "Runtime": 98,
    "Poster_Path": "/uPkiecNHlBdSlQVG6s1NN2FLluF.jpg",
    "Genres": "Comedy",
    "Keywords": "[{\"id\": 2920, \"name\": \"cheerleader\"}, {\"id\": 6075, \"name\": \"sport\"}, {\"id\": 6270, \"name\": \"high school\"}, {\"id\": 10809, \"name\": \"teenage girl\"}, {\"id\": 11672, \"name\": \"cheerleading\"}, {\"id\": 40905, \"name\": \"cheering crowd\"}, {\"id\": 179431, \"name\": \"duringcreditsstinger\"}]",
    "Director": "Peyton Reed",
    "budget": 28000000,
    "revenue": 90449929,
    "production_companies": "Beacon Communications",
    "Cast": "Kirsten Dunst, Jesse Bradford, Eliza Dushku",
    "clean_text": "bring toro cheerleading squad rancho carne high school san diego get spirit spunk sass killer routine s sure land national championship trophy sixth year row newlyelected team captain torrance toros road total cheer glory take shady turn discover perfectlychoreographe routine fact steal good move win comedy peyton reed kirsten dunst jesse bradford eliza dushku 2000"
}