{
    "Title": "The Indian in the Cupboard",
    "Overview": "A nine-year-old boy gets a plastic Indian and a cupboard for his birthday and finds himself involved in adventure when the Indian comes to life and befriends him.",
    "Tagline": "Unknown",
    "Homepage": "Unknown",
    "Release_Date": "1995-07-14",
    "Vote_Average": 6.404,
    "Runtime": 96,
    "Poster_Path": "/ozQAmW85tTJu2dhRe3evzyY03Nb.jpg",
    "Genres": "Adventure, Family, Fantasy",
    "Keywords": "[{\"id\": 1990, \"name\": \"cupboard\"}, {\"id\": 6186, \"name\": \"games\"}, {\"id\": 6300, \"name\": \"puppet\"}, {\"id\": 33465, \"name\": \"parallel world\"}, {\"id\": 187065, \"name\": \"toy comes to life\"}]",
    "Director": "Frank Oz",
    "budget": 45000000,
    "revenue": 0,
    "production_companies": "Paramount Pictures, Columbia Pictures Corporation, The Kennedy/Marshall Company",
    "Cast": "Hal Scardino, Litefoot, Lindsay Crouse"
}