{
    "Title": "The B\u00e9lier Family",
    "Overview": "The whole B\u00e9lier family is deaf, except for sixteen year old Paula who is the important translator in her parents' day to day life especially when it comes to matters concerning the family farm. When her music teacher discovers she has a fantastic singing voice and she gets an opportunity to enter a big Radio France contest the whole family's future is set up for big changes.",
    "Tagline": "Unknown",
    "Homepage": "Unknown",
    "Release_Date": "2014-12-17",
    "Vote_Average": 6.926,
    "Runtime": 105,
    "Poster_Path": "/kAQeZUZ1pMTSjSF3d6eBZClFGgN.jpg",
    "Genres": "Comedy, Music, Drama",
    "Keywords": "[{\"id\": 1643, \"name\": \"deafness\"}, {\"id\": 6027, \"name\": \"music\"}, {\"id\": 10683, \"name\": \"coming of age\"}, {\"id\": 10809, \"name\": \"teenage girl\"}, {\"id\": 12990, \"name\": \"singing\"}, {\"id\": 18035, \"name\": \"family\"}, {\"id\": 188953, \"name\": \"sign language\"}]",
    "Director": "Eric Lartigau",
    "budget": 11000000,
    "revenue": 0,
    "production_companies": "France 2 Cin\u00e9ma, Mars Films, Nexus Factory, Umedia, Jerico, Vend\u00f4me Production, Quarante 12 Films",
    "Cast": "Louane Emera, Karin Viard, Fran\u00e7ois Damiens"
}