{
    "Title": "Shakespeare in Love",
    "Overview": "Young Shakespeare is forced to stage his latest comedy, \"Romeo and Ethel, the Pirate's Daughter,\" before it's even written. When a lovely noblewoman auditions for a role, they fall into forbidden love -- and his play finds a new life (and title). As their relationship progresses, Shakespeare's comedy soon transforms into tragedy.",
    "Tagline": "Love is the only inspiration.",
    "Homepage": "Unknown",
    "Release_Date": "1998-12-11",
    "Vote_Average": 6.868,
    "Runtime": 123,
    "Poster_Path": "/iNCTveBiq7jQ4Av4ynWSdWXN6Cc.jpg",
    "Genres": "Romance, History, Comedy",
    "Keywords": "[{\"id\": 497, \"name\": \"shakespeare\"}, {\"id\": 2038, \"name\": \"love of one's life\"}, {\"id\": 3089, \"name\": \"oscar award\"}, {\"id\": 4326, \"name\": \"theatre play\"}, {\"id\": 4333, \"name\": \"theatre group\"}, {\"id\": 5914, \"name\": \"writer's block\"}, {\"id\": 6034, \"name\": \"theatre milieu\"}, {\"id\": 10818, \"name\": \"author\"}, {\"id\": 190531, \"name\": \"speculative\"}, {\"id\": 190532, \"name\": \"false history\"}]",
    "Director": "John Madden",
    "budget": 25000000,
    "revenue": 289317794,
    "production_companies": "Miramax Films, Universal Pictures, Bedford Falls Productions",
    "Cast": "Joseph Fiennes, Gwyneth Paltrow, Geoffrey Rush"
}