{
    "Title": "The Book of Life",
    "Overview": "The journey of Manolo, a young man who is torn between fulfilling the expectations of his family and following his heart. Before choosing which path to follow, he embarks on an incredible adventure that spans three fantastical worlds where he must face his greatest fears.",
    "Tagline": "A blast of fun.",
    "Homepage": "https://family.20thcenturystudios.com/movies/the-book-of-life",
    "Release_Date": "2014-10-01",
    "Vote_Average": 7.533,
    "Runtime": 95,
    "Poster_Path": "/aotTZos5KswgCryEzx2rlOjFsm1.jpg",
    "Genres": "Animation, Adventure, Comedy, Family, Fantasy",
    "Keywords": "[{\"id\": 128, \"name\": \"love triangle\"}, {\"id\": 6155, \"name\": \"afterlife\"}, {\"id\": 209789, \"name\": \"day of the dead\"}, {\"id\": 209790, \"name\": \"bullfighting\"}]",
    "Director": "Jorge R. Gutierrez",
    "budget": 50000000,
    "revenue": 97437106,
    "production_companies": "Twentieth Century Fox Film Corporation, Reel FX Creative Studios, Twentieth Century Fox Animation, Chatrone",
    "Cast": "Diego Luna, Channing Tatum, Zoe Saldana"
}