{
    "Title": "Away We Go",
    "Overview": "Verona and Burt have moved to Colorado to be close to Burt's parents but, with Veronica expecting their first child, Burt's parents decide to move to Belgium, now leaving them in a place they hate and without a support structure in place. They set off on a whirlwind tour of of disparate locations where they have friends or relatives, sampling not only different cities and climates but also different families. Along the way they realize that the journey is less about discovering where they want to live and more about figuring out what type of parents they want to be.",
    "Tagline": "Unknown",
    "Homepage": "Unknown",
    "Release_Date": "2009-06-05",
    "Vote_Average": 6.613,
    "Runtime": 98,
    "Poster_Path": "/bcN8sdoAPZae2Et1klD0iWRdSnZ.jpg",
    "Genres": "Drama, Comedy, Romance",
    "Keywords": "[{\"id\": 10131, \"name\": \"interracial relationship\"}, {\"id\": 168468, \"name\": \"dead father\"}, {\"id\": 168469, \"name\": \"reference to bob dylan\"}, {\"id\": 168471, \"name\": \"biracial\"}, {\"id\": 168472, \"name\": \"bedtime story\"}, {\"id\": 168477, \"name\": \"unmarried couple\"}, {\"id\": 168479, \"name\": \"medical illustrator\"}, {\"id\": 168481, \"name\": \"disguised voice\"}, {\"id\": 168482, \"name\": \"reference to huckleberry finn\"}, {\"id\": 168483, \"name\": \"student protest\"}, {\"id\": 168485, \"name\": \"sonogram\"}, {\"id\": 168486, \"name\": \"expectant grandmother\"}, {\"id\": 168490, \"name\": \"dead parents\"}, {\"id\": 168491, \"name\": \"testicles\"}]",
    "Director": "Sam Mendes",
    "budget": 17000000,
    "revenue": 14899417,
    "production_companies": "Neal Street Productions, Focus Features, Big Beach Films",
    "Cast": "John Krasinski, Maya Rudolph, Carmen Ejogo"
}