{
    "Title": "Seabiscuit",
    "Overview": "True story of the undersized Depression-era racehorse whose victories lifted not only the spirits of the team behind it but also those of their nation.",
    "Tagline": "The hopes of a nation rode on a long shot.",
    "Homepage": "http://www.seabiscuitmovie.com/",
    "Release_Date": "2003-07-22",
    "Vote_Average": 7.001,
    "Runtime": 141,
    "Poster_Path": "/5m7NfZvxYsSm2YBCJ2VPQf8ziKr.jpg",
    "Genres": "Drama, History",
    "Keywords": "[{\"id\": 643, \"name\": \"horse race\"}, {\"id\": 2355, \"name\": \"american dream\"}, {\"id\": 3525, \"name\": \"racehorse\"}, {\"id\": 5571, \"name\": \"great depression\"}]",
    "Director": "Gary Ross",
    "budget": 87000000,
    "revenue": 148336445,
    "production_companies": "Universal Pictures, Spyglass Entertainment, The Kennedy/Marshall Company, DreamWorks Pictures, Touchstone Pictures",
    "Cast": "Jeff Bridges, David McCullough, Chris Cooper",
    "clean_text": "seabiscuit true story undersized depressionera racehorse victory lift spirit team nation hope nation ride long shot drama history gary ross jeff bridges david mccullough chris cooper 2003"
}