{
    "Title": "Children of Men",
    "Overview": "In 2027, in a chaotic world in which humans can no longer procreate, a former activist agrees to help transport a miraculously pregnant woman to a sanctuary at sea, where her child's birth may help scientists save the future of humankind.",
    "Tagline": "The future's a thing of the past.",
    "Homepage": "http://www.universalstudiosentertainment.com/children-of-men/",
    "Release_Date": "2006-09-22",
    "Vote_Average": 7.605,
    "Runtime": 109,
    "Poster_Path": "/k9IAS4TehZFcKi4HVByxZNPfqex.jpg",
    "Genres": "Drama, Action, Thriller, Science Fiction",
    "Keywords": "[{\"id\": 318, \"name\": \"police state\"}, {\"id\": 458, \"name\": \"hippie\"}, {\"id\": 526, \"name\": \"rebel\"}, {\"id\": 2618, \"name\": \"miracle\"}, {\"id\": 2964, \"name\": \"future\"}, {\"id\": 4565, \"name\": \"dystopia\"}, {\"id\": 4630, \"name\": \"chaos\"}, {\"id\": 4995, \"name\": \"aging\"}, {\"id\": 5885, \"name\": \"childlessness\"}, {\"id\": 6150, \"name\": \"faith\"}, {\"id\": 10349, \"name\": \"survival\"}, {\"id\": 17985, \"name\": \"birth\"}, {\"id\": 41589, \"name\": \"dying\"}]",
    "Director": "Alfonso Cuar\u00f3n",
    "budget": 76000000,
    "revenue": 69959751,
    "production_companies": "Universal Pictures, Strike Entertainment, Hit & Run Productions",
    "Cast": "Clive Owen, Michael Caine, Julianne Moore"
}