{
    "Title": "The Thirteenth Floor",
    "Overview": "Los Angeles. A wealthy man, known as Mr. Fuller, discovers a shocking secret about the world he lives in. Fearing for his life, he leaves a desperate message for a friend of his in the most unexpected place.",
    "Tagline": "Question reality.",
    "Homepage": "Unknown",
    "Release_Date": "1999-04-16",
    "Vote_Average": 7.023,
    "Runtime": 101,
    "Poster_Path": "/7oaie3ZBc9UuWZLF24crro1pone.jpg",
    "Genres": "Thriller, Science Fiction, Mystery",
    "Keywords": "[{\"id\": 310, \"name\": \"artificial intelligence\"}, {\"id\": 2423, \"name\": \"simulation\"}, {\"id\": 4286, \"name\": \"computer program\"}, {\"id\": 4563, \"name\": \"virtual reality\"}, {\"id\": 4565, \"name\": \"dystopia\"}, {\"id\": 9826, \"name\": \"murder\"}, {\"id\": 12670, \"name\": \"los angeles\"}]",
    "Director": "Josef Rusnak",
    "budget": 16000000,
    "revenue": 18564088,
    "production_companies": "Columbia Pictures, Centropolis Film Productions",
    "Cast": "Craig Bierko, Armin Mueller-Stahl, Gretchen Mol"
}