{
    "Title": "Over the Hedge",
    "Overview": "A scheming raccoon fools a mismatched family of forest creatures into helping him repay a debt of food, by invading the new suburban sprawl that popped up while they were hibernating – and learns a lesson about family himself.",
    "Tagline": "Taking back the neighborhood... One snack at a time.",
    "Homepage": "Unknown",
    "Release_Date": "2006-05-17",
    "Vote_Average": 6.544,
    "Runtime": 83,
    "Poster_Path": "/PHNurftfUJTStsTgIkaxglvm2k.jpg",
    "Genres": "Family, Comedy, Animation",
    "Keywords": "[{\"id\": 990, \"name\": \"squirrel\"}, {\"id\": 1240, \"name\": \"eating and drinking\"}, {\"id\": 1950, \"name\": \"vororte\"}, {\"id\": 2105, \"name\": \"garden\"}, {\"id\": 2522, \"name\": \"grizzly bear\"}, {\"id\": 2847, \"name\": \"entrapment\"}, {\"id\": 2922, \"name\": \"suburbian idyll\"}, {\"id\": 3700, \"name\": \"garbage\"}, {\"id\": 5774, \"name\": \"forest\"}, {\"id\": 6362, \"name\": \"turtle\"}, {\"id\": 7125, \"name\": \"hiding in a garbage container\"}, {\"id\": 7948, \"name\": \"skunk\"}, {\"id\": 7949, \"name\": \"racoon\"}, {\"id\": 18165, \"name\": \"animal\"}]",
    "Director": "Karey Kirkpatrick",
    "budget": 80000000,
    "revenue": 343397247,
    "production_companies": "Pacific Data Images (PDI), DreamWorks Animation",
    "Cast": "Bruce Willis, Garry Shandling, Steve Carell",
    "clean_text": "hedge scheming raccoon fool mismatch family forest creature help repay debt food invade new suburban sprawl pop hibernate – learn lesson family take neighborhood one snack time family comedy animation karey kirkpatrick bruce willis garry shandle steve carell 2006"
}