{
    "Title": "The Matrix Revolutions",
    "Overview": "The human city of Zion defends itself against the massive invasion of the machines as Neo fights to end the war at another front while also opposing the rogue Agent Smith.",
    "Tagline": "Everything that has a beginning has an end.",
    "Homepage": "Unknown",
    "Release_Date": "2003-11-05",
    "Vote_Average": 6.71,
    "Runtime": 129,
    "Poster_Path": "/qEWiBXJGXK28jGBAm8oFKKTB0WD.jpg",
    "Genres": "Adventure, Action, Thriller, Science Fiction",
    "Keywords": "[{\"id\": 83, \"name\": \"saving the world\"}, {\"id\": 310, \"name\": \"artificial intelligence\"}, {\"id\": 312, \"name\": \"man vs machine\"}, {\"id\": 334, \"name\": \"flying\"}, {\"id\": 490, \"name\": \"philosophy\"}, {\"id\": 663, \"name\": \"fortune teller\"}, {\"id\": 780, \"name\": \"kung fu\"}, {\"id\": 1001, \"name\": \"underground world\"}, {\"id\": 1373, \"name\": \"killer robot\"}, {\"id\": 1530, \"name\": \"temple\"}, {\"id\": 1552, \"name\": \"subway\"}, {\"id\": 1566, \"name\": \"dream\"}, {\"id\": 1670, \"name\": \"sun\"}, {\"id\": 1701, \"name\": \"hero\"}, {\"id\": 1721, \"name\": \"fight\"}, {\"id\": 2725, \"name\": \"sunlight\"}, {\"id\": 2812, \"name\": \"computer virus\"}, {\"id\": 2849, \"name\": \"key\"}, {\"id\": 2964, \"name\": \"future\"}, {\"id\": 3219, \"name\": \"precognition\"}, {\"id\": 3222, \"name\": \"super computer\"}, {\"id\": 3223, \"name\": \"machine town\"}, {\"id\": 3225, \"name\": \"ying yang\"}, {\"id\": 3737, \"name\": \"dying and death\"}, {\"id\": 4563, \"name\": \"virtual reality\"}, {\"id\": 4565, \"name\": \"dystopia\"}, {\"id\": 6104, \"name\": \"computer\"}, {\"id\": 6150, \"name\": \"faith\"}, {\"id\": 6193, \"name\": \"world religion\"}, {\"id\": 6256, \"name\": \"truth\"}, {\"id\": 10084, \"name\": \"rescue\"}, {\"id\": 10364, \"name\": \"mission\"}, {\"id\": 12190, \"name\": \"cyberpunk\"}, {\"id\": 187056, \"name\": \"woman director\"}, {\"id\": 220232, \"name\": \"yin yang\"}, {\"id\": 221385, \"name\": \"gnosticism\"}]",
    "Director": "Lilly Wachowski",
    "budget": 150000000,
    "revenue": 424988211,
    "production_companies": "Village Roadshow Pictures, NPV Entertainment, Silver Pictures, Warner Bros.",
    "Cast": "Keanu Reeves, Laurence Fishburne, Carrie-Anne Moss"
}