{
    "Title": "Sinister",
    "Overview": "True-crime writer Ellison Oswald is in a slump; he hasn't had a best seller in more than 10 years and is becoming increasingly desperate for a hit. So, when he discovers the existence of a snuff film showing the deaths of a family, he vows to solve the mystery. He moves his own family into the victims' home and gets to work. However, when old film footage and other clues hint at the presence of a supernatural force, Ellison learns that living in the house may be fatal.",
    "Tagline": "Once you see him, nothing can save you.",
    "Homepage": "Unknown",
    "Release_Date": "2012-03-29",
    "Vote_Average": 6.868,
    "Runtime": 110,
    "Poster_Path": "/nzx10sca3arCeYBAomHan4Q6wa1.jpg",
    "Genres": "Horror, Thriller, Mystery",
    "Keywords": "[{\"id\": 793, \"name\": \"drowning\"}, {\"id\": 904, \"name\": \"pennsylvania\"}, {\"id\": 1468, \"name\": \"child murderer\"}, {\"id\": 9775, \"name\": \"car set on fire\"}, {\"id\": 9826, \"name\": \"murder\"}, {\"id\": 11464, \"name\": \"bag over head\"}, {\"id\": 14546, \"name\": \"massacre\"}, {\"id\": 14755, \"name\": \"power outage\"}, {\"id\": 15292, \"name\": \"hanged man\"}, {\"id\": 15365, \"name\": \"held captive\"}, {\"id\": 33407, \"name\": \"hanging\"}, {\"id\": 34079, \"name\": \"death\"}, {\"id\": 155619, \"name\": \"attic\"}, {\"id\": 158111, \"name\": \"no opening credits\"}, {\"id\": 160329, \"name\": \"super-8\"}, {\"id\": 172992, \"name\": \"ghost child\"}, {\"id\": 182022, \"name\": \"filmed killing\"}, {\"id\": 185767, \"name\": \"crime novelist\"}]",
    "Director": "Scott Derrickson",
    "budget": 3000000,
    "revenue": 77712439,
    "production_companies": "Alliance Films, Blumhouse Productions, IM Global, Automatik Entertainment, Possessed Pictures",
    "Cast": "Ethan Hawke, Juliet Rylance, Vincent D'Onofrio"
}