{
    "Title": "Fantasia",
    "Overview": "Walt Disney's timeless masterpiece is an extravaganza of sight and sound! See the music come to life, hear the pictures burst into song and experience the excitement that is Fantasia over and over again.",
    "Tagline": "The most sensational sound you'll ever see!",
    "Homepage": "http://movies.disney.com/fantasia",
    "Release_Date": "1940-11-13",
    "Vote_Average": 7.359,
    "Runtime": 124,
    "Poster_Path": "/5m9njnidjR0syG2gpVPVgcEMB2X.jpg",
    "Genres": "Animation, Family",
    "Keywords": "[{\"id\": 3537, \"name\": \"orchestra\"}, {\"id\": 5783, \"name\": \"classical music\"}, {\"id\": 190719, \"name\": \"musical segments\"}]",
    "Director": "David Hand",
    "budget": 2280000,
    "revenue": 83320000,
    "production_companies": "Walt Disney Pictures",
    "Cast": "Deems Taylor, Walt Disney, Julietta Novis"
}