{
    "Title": "Sleepers",
    "Overview": "Two gangsters seek revenge on the state jail worker who during their stay at a youth prison sexually abused them. A sensational court hearing takes place to charge him for the crimes.",
    "Tagline": "Four friends have made a mistake that will change their lives forever.",
    "Homepage": "Unknown",
    "Release_Date": "1996-10-18",
    "Vote_Average": 7.597,
    "Runtime": 147,
    "Poster_Path": "/yUpiEk2EojS9ZEXb3nIQonQCYYF.jpg",
    "Genres": "Crime, Drama, Thriller",
    "Keywords": "child abuse, sadistic, sexual abuse, pastor, repayment, juvenile prison, court case, pub, court, juvenile delinquent, child",
    "Director": "Barry Levinson",
    "budget": 44000000,
    "revenue": 165615285,
    "production_companies": "Propaganda Films, Warner Bros., Baltimore Pictures",
    "Cast": "Robert De Niro, Brad Pitt, Kevin Bacon"
}