{
    "Title": "How to Train Your Dragon",
    "Overview": "As the son of a Viking leader on the cusp of manhood, shy Hiccup Horrendous Haddock III faces a rite of passage: he must kill a dragon to prove his warrior mettle. But after downing a feared dragon, he realizes that he no longer wants to destroy it, and instead befriends the beast – which he names Toothless – much to the chagrin of his warrior father.",
    "Tagline": "One adventure will change two worlds",
    "Homepage": "http://www.howtotrainyourdragon.com/",
    "Release_Date": "2010-03-18",
    "Vote_Average": 7.813,
    "Runtime": 98,
    "Poster_Path": "/ygGmAO60t8GyqUo9xYeYxSZAR3b.jpg",
    "Genres": "Fantasy, Adventure, Animation, Family",
    "Keywords": "[{\"id\": 334, \"name\": \"flying\"}, {\"id\": 1318, \"name\": \"blacksmith\"}, {\"id\": 1395, \"name\": \"arena\"}, {\"id\": 2041, \"name\": \"island\"}, {\"id\": 3752, \"name\": \"night\"}, {\"id\": 3799, \"name\": \"ship\"}, {\"id\": 4613, \"name\": \"training\"}, {\"id\": 5331, \"name\": \"village\"}, {\"id\": 5774, \"name\": \"forest\"}, {\"id\": 5895, \"name\": \"viking\"}, {\"id\": 6054, \"name\": \"friendship\"}, {\"id\": 6253, \"name\": \"ignorance\"}, {\"id\": 8044, \"name\": \"flight\"}, {\"id\": 9109, \"name\": \"nest\"}, {\"id\": 12554, \"name\": \"dragon\"}, {\"id\": 14643, \"name\": \"battle\"}, {\"id\": 18543, \"name\": \"combat\"}, {\"id\": 172784, \"name\": \"well\"}, {\"id\": 192913, \"name\": \"warrior\"}]",
    "Director": "Chris Sanders",
    "budget": 165000000,
    "revenue": 494878759,
    "production_companies": "DreamWorks Animation, Vertigo Entertainment, Mad Hatter Entertainment",
    "Cast": "Jay Baruchel, Gerard Butler, Craig Ferguson",
    "clean_text": "train dragon son vike leader cusp manhood shy hiccup horrendous haddock iii face rite passage kill dragon prove warrior mettle down feared dragon realize long want destroy instead befriend beast – name toothless – chagrin warrior father one adventure change two world fantasy adventure animation family chris sanders jay baruchel gerard butler craig ferguson 2010"
}