{
    "Title": "The Purge: Anarchy",
    "Overview": "One night per year, the government sanctions a 12-hour period in which citizens can commit any crime they wish -- including murder -- without fear of punishment or imprisonment. Leo, a sergeant who lost his son, plans a vigilante mission of revenge during the mayhem. However, instead of a death-dealing avenger, he becomes the unexpected protector of four innocent strangers who desperately need his help if they are to survive the night.",
    "Tagline": "Welcome to America where one night a year all crime is legal",
    "Homepage": "Unknown",
    "Release_Date": "2014-07-17",
    "Vote_Average": 6.649,
    "Runtime": 104,
    "Poster_Path": "/f2HD5iVhJWWv72QVWThUKk09zYy.jpg",
    "Genres": "Horror, Thriller",
    "Keywords": "[{\"id\": 992, \"name\": \"bus\"}, {\"id\": 1376, \"name\": \"assault rifle\"}, {\"id\": 1589, \"name\": \"sniper\"}, {\"id\": 3544, \"name\": \"machete\"}, {\"id\": 4565, \"name\": \"dystopia\"}, {\"id\": 6259, \"name\": \"psychopath\"}, {\"id\": 9663, \"name\": \"sequel\"}, {\"id\": 9748, \"name\": \"revenge\"}, {\"id\": 9826, \"name\": \"murder\"}, {\"id\": 10349, \"name\": \"survival\"}, {\"id\": 14735, \"name\": \"motorcycle\"}, {\"id\": 14819, \"name\": \"violence\"}, {\"id\": 15068, \"name\": \"one day\"}, {\"id\": 15069, \"name\": \"masked man\"}, {\"id\": 33632, \"name\": \"apartment\"}, {\"id\": 34079, \"name\": \"death\"}, {\"id\": 50009, \"name\": \"survival horror\"}, {\"id\": 187028, \"name\": \"gatling gun\"}]",
    "Director": "James DeMonaco",
    "budget": 9000000,
    "revenue": 108782847,
    "production_companies": "Universal Pictures, Why Not Productions, Platinum Dunes, Blumhouse Productions, 5150 Action",
    "Cast": "Frank Grillo, Carmen Ejogo, Zach Gilford",
    "clean_text": "purge anarchy one night year government sanction 12hour period citizen commit crime wish   include murder   fear punishment imprisonment leo sergeant lose son plan vigilante mission revenge mayhem instead deathdeale avenger unexpected protector four innocent stranger desperately need help survive night welcome america one night year crime legal horror thriller james demonaco frank grillo carmen ejogo zach gilford 2014"
}