{
    "Title": "Good Luck Chuck",
    "Overview": "Cursed since childhood, dentist Charlie Logan cannot find the right woman. Even worse, he learns that each of his ex-girlfriends finds true love with the man she meets after her relationship with him ends. Hearing of Charlie's reputation as a good-luck charm, women from all over line up for a quick tryst. But when Charlie meets the woman of his dreams, he must find a way to break the curse or risk losing her to the next man she meets.",
    "Tagline": "He has to break his curse before she breaks his heart.",
    "Homepage": "http://www.goodluckchuckthemovie.com/",
    "Release_Date": "2007-09-21",
    "Vote_Average": 5.907,
    "Runtime": 101,
    "Poster_Path": "/eGxaRbDfxBWPysoxkOfYgkwflxJ.jpg",
    "Genres": "Comedy, Romance",
    "Keywords": "[{\"id\": 572, \"name\": \"sex\"}, {\"id\": 2269, \"name\": \"aquarium\"}, {\"id\": 2483, \"name\": \"nudity\"}, {\"id\": 2864, \"name\": \"one-night stand\"}, {\"id\": 3582, \"name\": \"bride\"}, {\"id\": 5756, \"name\": \"man-woman relation\"}, {\"id\": 9673, \"name\": \"love\"}, {\"id\": 10541, \"name\": \"curse\"}, {\"id\": 13027, \"name\": \"wedding\"}, {\"id\": 33780, \"name\": \"dentist\"}, {\"id\": 156866, \"name\": \"based on short story\"}, {\"id\": 179431, \"name\": \"duringcreditsstinger\"}]",
    "Director": "Mark Helfrich",
    "budget": 25000000,
    "revenue": 59192128,
    "production_companies": "Lionsgate, Karz Entertainment",
    "Cast": "Dane Cook, Jessica Alba, Dan Fogler"
}