{
    "Title": "The Words",
    "Overview": "The Words follows young writer Rory Jansen who finally achieves long sought after literary success after publishing the next great American novel. There's only one catch - he didn't write it. As the past comes back to haunt him and his literary star continues to rise, Jansen is forced to confront the steep price that must be paid for stealing another man's work, and for placing ambition and success above life's most fundamental three words.",
    "Tagline": "There's more than one way to take a life.",
    "Homepage": "http://www.thewordsmovie.com/",
    "Release_Date": "2012-09-07",
    "Vote_Average": 6.655,
    "Runtime": 96,
    "Poster_Path": "/aJtPLZS7tlpiQl6pEr8H42K565x.jpg",
    "Genres": "Drama, Thriller",
    "Keywords": "[{\"id\": 180404, \"name\": \"plagiarized book\"}, {\"id\": 180405, \"name\": \"stolen novel\"}, {\"id\": 180412, \"name\": \"plagiarized novel\"}, {\"id\": 180413, \"name\": \"aspiring writer\"}]",
    "Director": "Brian Klugman",
    "budget": 6000000,
    "revenue": 13231461,
    "production_companies": "CBS Films, Also Known As Pictures",
    "Cast": "Bradley Cooper, Zoe Saldana, Jeremy Irons",
    "clean_text": "word word follow young writer rory jansen finally achieves long seek literary success publish great american novel s one catch   not write past come haunt literary star continue rise jansen force confront steep price pay steal man work place ambition success life fundamental three word s one way life drama thriller brian klugman bradley cooper zoe saldana jeremy iron 2012"
}