{
    "Title": "Terminator 3: Rise of the Machines",
    "Overview": "It's been 10 years since John Connor saved Earth from Judgment Day, and he's now living under the radar, steering clear of using anything Skynet can trace. That is, until he encounters T-X, a robotic assassin ordered to finish what T-1000 started. Good thing Connor's former nemesis, the Terminator, is back to aid the now-adult Connor \u2026 just like he promised.",
    "Tagline": "The Machines Will Rise.",
    "Homepage": "https://www.warnerbros.com/movies/terminator-3-rise-machines/",
    "Release_Date": "2003-07-02",
    "Vote_Average": 6.145,
    "Runtime": 109,
    "Poster_Path": "/qAnafzrd9Y5pVTWAP0tSDDMPzTR.jpg",
    "Genres": "Action, Thriller, Science Fiction",
    "Keywords": "[{\"id\": 83, \"name\": \"saving the world\"}, {\"id\": 310, \"name\": \"artificial intelligence\"}, {\"id\": 312, \"name\": \"man vs machine\"}, {\"id\": 679, \"name\": \"cyborg\"}, {\"id\": 1373, \"name\": \"killer robot\"}, {\"id\": 1381, \"name\": \"sun glasses\"}, {\"id\": 2650, \"name\": \"leather jacket\"}, {\"id\": 2651, \"name\": \"nanotechnology\"}, {\"id\": 2732, \"name\": \"rocket launcher\"}, {\"id\": 2733, \"name\": \"firemen\"}, {\"id\": 2735, \"name\": \"veterinarian\"}, {\"id\": 2736, \"name\": \"fire engine\"}, {\"id\": 4565, \"name\": \"dystopia\"}, {\"id\": 15106, \"name\": \"psychiatrist\"}]",
    "Director": "Jonathan Mostow",
    "budget": 200000000,
    "revenue": 435000000,
    "production_companies": "Columbia Pictures, Intermedia Films, Warner Bros., C-2 Pictures, IMF Internationale Medien und Film GmbH & Co. 3. Produktions KG, Mostow/Lieberman Productions",
    "Cast": "Arnold Schwarzenegger, Nick Stahl, Claire Danes"
}