{
    "Title": "Boyhood",
    "Overview": "The film tells a story of a divorced couple trying to raise their young son. The story follows the boy for twelve years, from first grade at age 6 through 12th grade at age 17-18, and examines his relationship with his parents as he grows.",
    "Tagline": "12 years in the making.",
    "Homepage": "http://www.ifcfilms.com/films/boyhood",
    "Release_Date": "2014-06-05",
    "Vote_Average": 7.509,
    "Runtime": 166,
    "Poster_Path": "/2BvtvDUyxiMJ4dmKfiQf4qdOHQN.jpg",
    "Genres": "Drama",
    "Keywords": "[{\"id\": 1850, \"name\": \"daily life\"}, {\"id\": 2783, \"name\": \"family's daily life\"}, {\"id\": 5768, \"name\": \"urban life\"}, {\"id\": 9825, \"name\": \"growing up\"}, {\"id\": 10303, \"name\": \"domestic abuse\"}, {\"id\": 10683, \"name\": \"coming of age\"}, {\"id\": 15025, \"name\": \"parenting\"}, {\"id\": 15160, \"name\": \"divorce\"}, {\"id\": 18035, \"name\": \"family\"}, {\"id\": 184439, \"name\": \"divorced parents\"}, {\"id\": 212643, \"name\": \"abusive husband\"}]",
    "Director": "Richard Linklater",
    "budget": 4000000,
    "revenue": 44349000,
    "production_companies": "IFC Films, Detour Filmproduction",
    "Cast": "Ellar Coltrane, Patricia Arquette, Ethan Hawke",
    "clean_text": "boyhood film tell story divorced couple try raise young son story follow boy twelve year first grade age 6 12th grade age 1718 examine relationship parent grow 12 year make drama richard linklater ellar coltrane patricia arquette ethan hawke 2014"
}