{
    "Title": "The Quick and the Dead",
    "Overview": "A mysterious woman comes to compete in a quick-draw elimination tournament, in a town taken over by a notorious gunman.",
    "Tagline": "Think you're quick enough?",
    "Homepage": "Unknown",
    "Release_Date": "1995-02-09",
    "Vote_Average": 6.518,
    "Runtime": 107,
    "Poster_Path": "/jhEmrXJpP6F3cqwyLjvgBgxxxFA.jpg",
    "Genres": "Western, Action",
    "Keywords": "[{\"id\": 75, \"name\": \"gunslinger\"}, {\"id\": 9748, \"name\": \"revenge\"}, {\"id\": 9930, \"name\": \"prairie\"}, {\"id\": 10950, \"name\": \"shootout\"}, {\"id\": 13132, \"name\": \"pistol\"}]",
    "Director": "Sam Raimi",
    "budget": 32000000,
    "revenue": 18552460,
    "production_companies": "TriStar Pictures",
    "Cast": "Sharon Stone, Gene Hackman, Russell Crowe",
    "clean_text": "quick dead mysterious woman come compete quickdraw elimination tournament town take notorious gunman think quick western action sam raimi sharon stone gene hackman russell crowe 1995"
}