{
    "Title": "Hidalgo",
    "Overview": "Set in 1890, this is the story of a Pony Express courier who travels to Arabia to compete with his horse, Hidalgo, in a dangerous race for a massive contest prize, in an adventure that sends the pair around the world...",
    "Tagline": "Unbridled. Unbroken. Unbeaten.",
    "Homepage": "Unknown",
    "Release_Date": "2004-02-04",
    "Vote_Average": 6.811,
    "Runtime": 136,
    "Poster_Path": "/iGzENlBPYJEFWZnye4t3nqWSSp1.jpg",
    "Genres": "Western, Adventure, Action",
    "Keywords": "[{\"id\": 643, \"name\": \"horse race\"}, {\"id\": 2673, \"name\": \"horse\"}, {\"id\": 3525, \"name\": \"racehorse\"}]",
    "Director": "Joe Johnston",
    "budget": 100000000,
    "revenue": 108103450,
    "production_companies": "Casey Silver Productions, Touchstone Pictures, Dune Films",
    "Cast": "Viggo Mortensen, Zuleikha Robinson, Omar Sharif"
}