{
    "Title": "American Beauty",
    "Overview": "Lester Burnham, a depressed suburban father in a mid-life crisis, decides to turn his hectic life around after developing an infatuation with his daughter's attractive friend.",
    "Tagline": "Look closer.",
    "Homepage": "Unknown",
    "Release_Date": "1999-09-15",
    "Vote_Average": 8.0,
    "Runtime": 122,
    "Poster_Path": "/wby9315QzVKdW9BonAefg8jGTTb.jpg",
    "Genres": "Drama",
    "Keywords": "[{\"id\": 255, \"name\": \"male nudity\"}, {\"id\": 293, \"name\": \"female nudity\"}, {\"id\": 596, \"name\": \"adultery\"}, {\"id\": 1599, \"name\": \"midlife crisis\"}, {\"id\": 1862, \"name\": \"coming out\"}, {\"id\": 2201, \"name\": \"first time\"}, {\"id\": 2249, \"name\": \"camcorder\"}, {\"id\": 2389, \"name\": \"virgin\"}, {\"id\": 2483, \"name\": \"nudity\"}, {\"id\": 2559, \"name\": \"film maker\"}, {\"id\": 2918, \"name\": \"estate agent\"}, {\"id\": 8201, \"name\": \"satire\"}, {\"id\": 9957, \"name\": \"loneliness\"}, {\"id\": 10123, \"name\": \"dark comedy\"}, {\"id\": 10532, \"name\": \"suburbia\"}, {\"id\": 10683, \"name\": \"coming of age\"}, {\"id\": 10776, \"name\": \"marijuana\"}, {\"id\": 33611, \"name\": \"exercise\"}, {\"id\": 166123, \"name\": \"parent child relationship\"}, {\"id\": 224279, \"name\": \"bittersweet\"}, {\"id\": 229299, \"name\": \"affair\"}]",
    "Director": "Sam Mendes",
    "budget": 15000000,
    "revenue": 356296601,
    "production_companies": "DreamWorks SKG, Jinks/Cohen Company",
    "Cast": "Kevin Spacey, Annette Bening, Thora Birch"
}